marpyter/__init__.py
marpyter/_version.py
marpyter-0.1.0.data/data/share/jupyter/labextensions/marpyter/package.json
marpyter-0.1.0.data/data/share/jupyter/labextensions/marpyter/static/152.3b681059657b0207a9c2.js
marpyter-0.1.0.data/data/share/jupyter/labextensions/marpyter/static/155.a0d18ddbc5e62a53cb4e.js
marpyter-0.1.0.data/data/share/jupyter/labextensions/marpyter/static/271.44fda4313d1da0b89a99.js
marpyter-0.1.0.data/data/share/jupyter/labextensions/marpyter/static/271.44fda4313d1da0b89a99.js.LICENSE.txt
marpyter-0.1.0.data/data/share/jupyter/labextensions/marpyter/static/427.1110edb5440f5414a843.js
marpyter-0.1.0.data/data/share/jupyter/labextensions/marpyter/static/539.39c85f911c7256f8beea.js
marpyter-0.1.0.data/data/share/jupyter/labextensions/marpyter/static/747.3a677c706d45e7d43969.js
marpyter-0.1.0.data/data/share/jupyter/labextensions/marpyter/static/remoteEntry.be6d8ebed66aef89a1ca.js
marpyter-0.1.0.data/data/share/jupyter/labextensions/marpyter/static/style.js
marpyter-0.1.0.data/data/share/jupyter/labextensions/marpyter/static/third-party-licenses.json
marpyter-0.1.0.data/data/share/jupyter/labextensions/marpyter/install.json
marpyter-0.1.0.dist-info/METADATA
marpyter-0.1.0.dist-info/WHEEL
marpyter-0.1.0.dist-info/licenses/LICENSE
marpyter-0.1.0.dist-info/RECORD
